Metadata-Version: 2.1
Name: proxtaster
Version: 1.0.3
Summary: Пакет для проверки прокси
Home-page: https://gitlab.com/thewhatis/ptaster
Download-URL: https://gitlab.com/thewhatis/ptaster/dist/proxtaster-1.0.3.zip
Author: Whatis
Author-email: asdwdagwahwabe@gmail.com
License: GPL
Platform: any
Requires-Dist: aiohttp
Requires-Dist: aiohttp-proxy
Requires-Dist: fake-useragent
Requires-Dist: PyEventEmitter
